gh_auth/__init__.py
gh_auth/auth.py
gh_auth/exceptions.py
gh_auth-0.1.3.dist-info/WHEEL
gh_auth-0.1.3.dist-info/METADATA
gh_auth-0.1.3.dist-info/RECORD
