Metadata-Version: 2.1
Name: gh-auth
Version: 0.1.3
Summary: A simple Python library for web-based GitHub authentication.
Home-page: https://github.com/jasonalantolbert/gh-auth
License: MIT
Keywords: github,authentication
Author: Jason Tolbert
Author-email: jasonalantolbert@gmail.com
Requires-Python: >=3.9.0,<4.0.0
Classifier: License :: OSI Approved :: MIT License
Classifier: Programming Language :: Python :: 3
Classifier: Programming Language :: Python :: 3.9
Requires-Dist: halo (>=0.0.31,<0.0.32)
Requires-Dist: requests (>=2.25.1,<3.0.0)
Project-URL: Repository, https://github.com/jasonalantolbert/gh-auth
